pycuba/__init__.py
pymultinest/__init__.py
pymultinest/analyse.py
pymultinest/plot.py
pymultinest/run.py
pymultinest/solve.py
pymultinest/watch.py
pymultinest-2.11.data/scripts/multinest_marginals.py
pymultinest-2.11.data/scripts/multinest_marginals_corner.py
pymultinest-2.11.data/scripts/multinest_marginals_fancy.py
pymultinest-2.11.dist-info/COPYING
pymultinest-2.11.dist-info/LICENSE
pymultinest-2.11.dist-info/METADATA
pymultinest-2.11.dist-info/WHEEL
pymultinest-2.11.dist-info/top_level.txt
pymultinest-2.11.dist-info/RECORD
