Metadata-Version: 1.2
Name: pymultinest
Version: 2.11
Summary: Access modules for the MultiNest and Cuba integration libraries
Home-page: http://johannesbuchner.github.com/PyMultiNest/
Author: Johannes Buchner
Author-email: johannes.buchner.acad@gmx.com
Maintainer: Johannes Buchner
Maintainer-email: johannes.buchner.acad@gmx.com
License: GPLv3
Platform: UNKNOWN
Requires: numpy (>=1.5)
Requires: matplotlib
Requires: scipy
Provides: pymultinest
Provides: pycuba
